LICENSE.txt
setup.cfg
setup.py
django_gas_drf.egg-info/PKG-INFO
django_gas_drf.egg-info/SOURCES.txt
django_gas_drf.egg-info/dependency_links.txt
django_gas_drf.egg-info/top_level.txt
gas_drf/__init__.py
gas_drf/apps.py
gas_drf/mixins.py
gas_drf/permissions.py
gas_drf/sites.py
gas_drf/gas/__init__.py
gas_drf/gas/users_drf_config.py
gas_drf/gas/users/__init__.py
gas_drf/gas/users/api_views.py
gas_drf/gas/users/serializers.py
gas_drf/tests/__init__.py
gas_drf/tests/test_permissions.py
gas_drf/tests/test_site.py
gas_drf/tests/urls.py