Metadata-Version: 2.1
Name: django-gas-drf
Version: 0.1.1
Summary: DRF support for django-gas
Home-page: https://git.negromate.rocks/shagi/gas-drf
Author: Ales (Shagi) Zabala Alava
Author-email: shagi@gisa-elkartea.org
License: GPLv3
Platform: UNKNOWN
Classifier: Environment :: Web Environment
Classifier: Framework :: Django
Classifier: Framework :: Django :: 3.1
Classifier: Intended Audience :: Developers
Classifier: License :: OSI Approved :: GNU General Public License v3 or later (GPLv3+)
Classifier: Operating System :: OS Independent
Classifier: Programming Language :: Python
Classifier: Programming Language :: Python :: 3
Classifier: Programming Language :: Python :: 3 :: Only
Classifier: Topic :: Internet :: WWW/HTTP
Classifier: Topic :: Internet :: WWW/HTTP :: Dynamic Content
License-File: LICENSE.txt
